trash_collector/__init__.py
trash_collector/__main__.py
trash_collector/create_file.py
trash_collector/db.py
trash_collector/search.py
trash_collector/utils.py
trash_collector-0.0.3.dist-info/METADATA
trash_collector-0.0.3.dist-info/WHEEL
trash_collector-0.0.3.dist-info/licenses/LICENSE
trash_collector-0.0.3.dist-info/RECORD
