Metadata-Version: 2.3
Name: trash_collector
Version: 0.0.3
Summary: Python cli to easily help clean old folders and free up disk space.
Project-URL: Homepage, https://github.com/Notenlish/trash_collector
Project-URL: Issues, https://github.com/Notenlish/trash_collector/issues
Author-email: "Notenlish (Ihsan Carkci)" <notenlish@gmail.com>
License-File: LICENSE
Keywords: cleaner,cleanup,disk space,garbage,garbage collector,trash,trash collector
Classifier: License :: OSI Approved :: MIT License
Classifier: Operating System :: OS Independent
Classifier: Programming Language :: Python :: 3
Requires-Python: >=3.8
Requires-Dist: colorama==0.4.6
Requires-Dist: pytest==8.0.1
Requires-Dist: shellingham==1.5.4
Requires-Dist: typer[all]==0.9.0
